turtle_conics/__init__.py
turtle_conics/all_curves.py
turtle_conics-0.2.2.dist-info/LICENSE.txt
turtle_conics-0.2.2.dist-info/METADATA
turtle_conics-0.2.2.dist-info/WHEEL
turtle_conics-0.2.2.dist-info/top_level.txt
turtle_conics-0.2.2.dist-info/RECORD
