Metadata-Version: 2.1
Name: turtle-conics
Version: 0.2.2
Summary: Creating different conic sections and curves
Home-page: https://github.com/Devansu-Yadav/My-First-Python-Package
Author: Devansu Yadav
Author-email: devansuyadav@gmail.com
License: UNKNOWN
Platform: UNKNOWN
Classifier: Programming Language :: Python :: 3
Classifier: License :: OSI Approved :: MIT License
Classifier: Operating System :: OS Independent
Requires-Python: >=3.6
